parsrt/__init__.py
parsrt/parsrt.py
parsrt-1.2.dist-info/LICENSE
parsrt-1.2.dist-info/METADATA
parsrt-1.2.dist-info/WHEEL
parsrt-1.2.dist-info/top_level.txt
parsrt-1.2.dist-info/RECORD
