Metadata-Version: 2.1
Name: parsrt
Version: 1.2
Summary: A minimalistic (100LOC) library to read SRT files into a workable format.
Home-page: https://github.com/vukgr/parsrt
Author: VukGr
Author-email: vuk.grujic.5@hotmail.com
License: MIT
Download-URL: https://github.com/user/parsrt/archive/v_10.tar.gz
Keywords: SRT,TINY,MINIMALISTIC,FAST
Platform: UNKNOWN
Classifier: Intended Audience :: Developers
Classifier: Topic :: Software Development :: Build Tools
Classifier: License :: OSI Approved :: MIT License
Classifier: Programming Language :: Python :: 3
Classifier: Programming Language :: Python :: 3.9
Classifier: Operating System :: OS Independent
